ntchat/__init__.py
ntchat/conf/__init__.py
ntchat/const/__init__.py
ntchat/const/notify_type.py
ntchat/const/send_type.py
ntchat/core/__init__.py
ntchat/core/mgr.py
ntchat/core/wechat.py
ntchat/exception/__init__.py
ntchat/utils/__init__.py
ntchat/utils/logger.py
ntchat/utils/singleton.py
ntchat/utils/xdg.py
ntchat/wc/__init__.py
ntchat/wc/helper_3.6.0.18.dat
ntchat/wc/wcprobe.cp38-win32.pyd
ntchat-0.1.20.dist-info/LICENSE
ntchat-0.1.20.dist-info/METADATA
ntchat-0.1.20.dist-info/WHEEL
ntchat-0.1.20.dist-info/top_level.txt
ntchat-0.1.20.dist-info/RECORD
