Metadata-Version: 2.1
Name: ntchat
Version: 0.1.20
Summary: About Conversational RPA SDK for Chatbot Makers
Home-page: https://github.com/smallevilbeast/ntchat
Author: evilbeast
Author-email: evilbeast@gmail.com
License: MIT
Keywords: wechat ntchat pywechat rebot
Classifier: Development Status :: 4 - Beta
Classifier: License :: OSI Approved :: MIT License
Classifier: Programming Language :: Python :: 3.6
Classifier: Programming Language :: Python :: 3.7
Classifier: Programming Language :: Python :: 3.8
Classifier: Programming Language :: Python :: 3.9
Classifier: Programming Language :: Python :: 3.10
Classifier: Programming Language :: Python :: 3.11
License-File: LICENSE
Requires-Dist: pyee
